{
  "song": "fresh",
  "bpm": 120,
  "op": "dad",
  "bf": "bf",
  "gf": "gf",
  "speedMultiplier": 1.4,
  "background": "stage",
  "bfNotes": [
    { "note": "left", "time": 2.195800000011921 },
    { "note": "right", "time": 2.7002000000178814 },
    { "note": "up", "time": 3.229 },
    { "note": "down", "time": 3.699800000011921 },
    { "note": "left", "time": 6.19609999999404 },
    { "note": "right", "time": 6.67590000000596 },
    { "note": "up", "time": 7.212200000017881 },
    { "note": "down", "time": 7.6525 },
    { "note": "left", "time": 10.33259999999404 },
    { "note": "up", "time": 10.620300000011921 },
    { "note": "right", "time": 11.156099999994039 },
    { "note": "up", "time": 14.420200000017882 },
    { "note": "left", "time": 14.685 },
    { "note": "right", "time": 14.908700000017882 },
    { "note": "right", "time": 15.15659999999404 },
    { "note": "up", "time": 18.78070000001788 },
    { "note": "down", "time": 19.0365 },
    { "note": "right", "time": 19.220200000017883 },
    { "note": "up", "time": 19.66040000000596 },
    { "note": "left", "time": 21.90840000000596 },
    { "note": "up", "time": 22.204599999994038 },
    { "note": "down", "time": 22.36470000001788 },
    { "note": "right", "time": 22.97220000001788 },
    { "note": "left", "time": 23.14820000001788 },
    { "note": "up", "time": 23.49290000000596 },
    { "note": "down", "time": 23.908800000011922 },
    { "note": "left", "time": 28.141200000017882 },
    { "note": "up", "time": 28.64480000001192 },
    { "note": "down", "time": 29.1485 },
    { "note": "right", "time": 29.596700000017883 },
    { "note": "up", "time": 30.1085 },
    { "note": "left", "time": 30.62070000001788 },
    { "note": "right", "time": 31.164800000011923 },
    { "note": "down", "time": 31.60459999999404 },
    { "note": "up", "time": 36.61270000001788 },
    { "note": "down", "time": 37.18109999999404 },
    { "note": "right", "time": 37.62109999999404 },
    { "note": "left", "time": 37.98870000001788 },
    { "note": "up", "time": 38.52509999999404 },
    { "note": "down", "time": 39.04480000001192 },
    { "note": "right", "time": 39.597099999994036 },
    { "note": "up", "time": 42.42880000001192 },
    { "note": "down", "time": 42.65309999999404 },
    { "note": "right", "time": 43.11680000001192 },
    { "note": "left", "time": 43.66130000001192 },
    { "note": "up", "time": 43.87740000000596 },
    { "note": "left", "time": 46.39859999999404 },
    { "note": "up", "time": 46.6935 },
    { "note": "down", "time": 46.8935 },
    { "note": "right", "time": 47.14120000001788 },
    { "note": "up", "time": 47.90890000000596 },
    { "note": "right", "time": 50.37359999999404 },
    { "note": "left", "time": 50.64570000001788 },
    { "note": "up", "time": 50.94909999999404 },
    { "note": "down", "time": 51.141300000011924 },
    { "note": "right", "time": 51.94140000000596 },
    { "note": "right", "time": 54.14090000000596 },
    { "note": "left", "time": 54.65570000001788 },
    { "note": "up", "time": 55.03709999999404 },
    { "note": "down", "time": 55.589300000011924 },
    { "note": "right", "time": 55.98220000001788 },
    { "note": "up", "time": 60.133800000011924 },
    { "note": "down", "time": 60.70190000000596 },
    { "note": "right", "time": 61.16520000001788 },
    { "note": "left", "time": 61.56530000001192 },
    { "note": "up", "time": 62.1335 },
    { "note": "down", "time": 62.61359999999404 },
    { "note": "right", "time": 63.14109999999404 },
    { "note": "left", "time": 63.56540000000596 },
    { "note": "right", "time": 68.6375 },
    { "note": "left", "time": 69.09370000001788 },
    { "note": "up", "time": 69.662 },
    { "note": "right", "time": 70.64559999999403 },
    { "note": "up", "time": 71.17390000000596 },
    { "note": "left", "time": 71.59120000001788 },
    { "note": "left", "time": 74.17520000001788 },
    { "note": "up", "time": 74.66980000001192 },
    { "note": "down", "time": 75.16559999999404 },
    { "note": "right", "time": 75.65390000000596 },
    { "note": "left", "time": 78.15809999999404 },
    { "note": "up", "time": 78.64730000001192 },
    { "note": "down", "time": 79.15780000001192 },
    { "note": "right", "time": 79.6295 }
  ],
  "opNotes": [
    { "note": "down", "time": 0.0, "hold": 0.0 },
    { "note": "right", "time": 0.5, "hold": 0.0 },
    { "note": "down", "time": 1.25, "hold": 0.0 },
    { "note": "up", "time": 1.5, "hold": 0.0 },
    { "note": "left", "time": 1.601199999988079 },
    { "note": "right", "time": 1.744699999988079 },
    { "note": "down", "time": 1.864800000011921 },
    { "note": "left", "time": 4.1845 },
    { "note": "right", "time": 4.6965 },
    { "note": "down", "time": 5.096800000011921 },
    { "note": "up", "time": 5.648900000005961 },
    { "note": "up", "time": 8.48109999999404 },
    { "note": "right", "time": 9.07259999999404 },
    { "note": "up", "time": 12.409 },
    { "note": "up", "time": 12.5785 },
    { "note": "down", "time": 12.88059999999404 },
    { "note": "right", "time": 13.11269999998808 },
    { "note": "left", "time": 16.465 },
    { "note": "right", "time": 16.85740000000596 },
    { "note": "down", "time": 17.01740000000596 },
    { "note": "up", "time": 17.24959999999404 },
    { "note": "right", "time": 17.74490000000596 },
    { "note": "up", "time": 20.07319999998808 },
    { "note": "down", "time": 20.23319999998808 },
    { "note": "right", "time": 20.881300000011922 },
    { "note": "left", "time": 21.185699999988078 },
    { "note": "right", "time": 21.977300000011923 },
    { "note": "left", "time": 22.20190000000596 },
    { "note": "up", "time": 24.169 },
    { "note": "down", "time": 24.65759999999404 },
    { "note": "right", "time": 25.169300000011923 },
    { "note": "left", "time": 25.6415 },
    { "note": "up", "time": 26.15330000001192 },
    { "note": "down", "time": 26.689300000011922 },
    { "note": "right", "time": 27.23359999999404 },
    { "note": "right", "time": 27.67319999998808 },
    { "note": "down", "time": 32.54559999999404 },
    { "note": "up", "time": 33.13840000000596 },
    { "note": "left", "time": 33.65780000001192 },
    { "note": "right", "time": 33.91340000000596 },
    { "note": "up", "time": 34.49730000001192 },
    { "note": "left", "time": 34.85740000000596 },
    { "note": "right", "time": 35.202300000011924 },
    { "note": "down", "time": 35.71319999998808 },
    { "note": "up", "time": 40.59380000001192 },
    { "note": "down", "time": 41.10619999998808 },
    { "note": "right", "time": 41.64969999998808 },
    { "note": "right", "time": 41.97780000001192 },
    { "note": "left", "time": 44.60169999998808 },
    { "note": "up", "time": 44.8905 },
    { "note": "down", "time": 45.1625 },
    { "note": "right", "time": 45.91340000000596 },
    { "note": "left", "time": 48.34740000000596 },
    { "note": "up", "time": 48.666 },
    { "note": "down", "time": 49.00169999998808 },
    { "note": "right", "time": 49.19369999998808 },
    { "note": "up", "time": 49.77 },
    { "note": "down", "time": 52.12230000001192 },
    { "note": "up", "time": 52.48190000000596 },
    { "note": "left", "time": 52.92240000000596 },
    { "note": "right", "time": 53.15380000001192 },
    { "note": "down", "time": 53.41809999999404 },
    { "note": "up", "time": 56.1705 },
    { "note": "down", "time": 56.68219999998808 },
    { "note": "right", "time": 57.178 },
    { "note": "left", "time": 57.64219999998808 },
    { "note": "up", "time": 58.21059999999404 },
    { "note": "down", "time": 58.66590000000596 },
    { "note": "right", "time": 59.17009999999404 },
    { "note": "left", "time": 59.64240000000596 },
    { "note": "down", "time": 64.68209999999404 },
    { "note": "up", "time": 65.17019999998809 },
    { "note": "down", "time": 65.68219999998809 },
    { "note": "down", "time": 66.21040000000596 },
    { "note": "right", "time": 66.65830000001192 },
    { "note": "left", "time": 67.194 },
    { "note": "left", "time": 67.65830000001192 },
    { "note": "up", "time": 74.21830000001192 },
    { "note": "down", "time": 76.22659999999404 },
    { "note": "up", "time": 76.71430000001192 },
    { "note": "right", "time": 77.067 },
    { "note": "left", "time": 77.65040000000596 }
  ]
}
